scglue/__init__.py
scglue/check.py
scglue/data.py
scglue/genomics.py
scglue/graph.py
scglue/metrics.py
scglue/num.py
scglue/plot.py
scglue/typehint.py
scglue/utils.py
scglue/models/__init__.py
scglue/models/base.py
scglue/models/data.py
scglue/models/dx.py
scglue/models/glue.py
scglue/models/nn.py
scglue/models/plugins.py
scglue/models/prob.py
scglue/models/sc.py
scglue/models/scclue.py
scglue/models/scglue.py
scglue-0.4.0.dist-info/licenses/LICENSE
scglue-0.4.0.dist-info/WHEEL
scglue-0.4.0.dist-info/METADATA
scglue-0.4.0.dist-info/RECORD
